DCP/ModelPlanner.py
DCP/VAEtorch.py
DCP/__init__.py
DCP/deep_predictor.py
DCP/flow.py
DCP/utils.py
dcpredictor-0.0.1.dist-info/LICENSE
dcpredictor-0.0.1.dist-info/METADATA
dcpredictor-0.0.1.dist-info/WHEEL
dcpredictor-0.0.1.dist-info/top_level.txt
dcpredictor-0.0.1.dist-info/RECORD
